demos/__init__.py
demos/program.py
pylidator/__init__.py
pylidator/validators.py
test/__init__.py
test/test_validators.py
pylidity-0.0.1.dist-info/LICENCE
pylidity-0.0.1.dist-info/METADATA
pylidity-0.0.1.dist-info/WHEEL
pylidity-0.0.1.dist-info/top_level.txt
pylidity-0.0.1.dist-info/RECORD
