Metadata-Version: 2.1
Name: pylidity
Version: 0.0.1
Summary: A validation library for python
License-File: LICENCE
